tendawifi/__init__.py
tendawifi-0.6.0.dist-info/LICENSE
tendawifi-0.6.0.dist-info/METADATA
tendawifi-0.6.0.dist-info/WHEEL
tendawifi-0.6.0.dist-info/top_level.txt
tendawifi-0.6.0.dist-info/RECORD
