Metadata-Version: 2.1
Name: tendawifi
Version: 0.6.0
Summary: Python package that allows to manage tenda router AC15.
Home-page: https://github.com/marc0u/tenda-wifi
Author: Marco Urriola
Author-email: marco.urriola@gmail.com
License: UNKNOWN
Platform: UNKNOWN
Classifier: Programming Language :: Python :: 3
Classifier: License :: OSI Approved :: MIT License
Classifier: Operating System :: OS Independent
Requires-Python: >=3.6
Requires-Dist: reqtry (<1.0,>=0.0.2)
